AUTHORS.rst
CONTRIBUTING.rst
HISTORY.rst
LICENSE.rst
MANIFEST.in
README.rst
requirements-dev.txt
requirements.txt
setup.py
django_sub_query.egg-info/PKG-INFO
django_sub_query.egg-info/SOURCES.txt
django_sub_query.egg-info/dependency_links.txt
django_sub_query.egg-info/requires.txt
django_sub_query.egg-info/top_level.txt
docs/Makefile
docs/authors.rst
docs/conf.py
docs/contributing.rst
docs/history.rst
docs/index.rst
docs/installation.rst
docs/make.bat
docs/readme.rst
docs/usage.rst
sub_query/__init__.py
sub_query/db/__init__.py
sub_query/db/backends/__init__.py
sub_query/db/backends/postgis/__init__.py
sub_query/db/backends/postgis/base.py
sub_query/db/backends/postgis/operations.py
sub_query/db/models/__init__.py
sub_query/db/models/query.py
sub_query/db/models/sql/__init__.py
sub_query/db/models/sql/compiler.py
sub_query/db/models/sql/query.py
sub_query/tests/__init__.py
sub_query/tests/db/__init__.py
sub_query/tests/db/backends/__init__.py
sub_query/tests/db/backends/postgis/__init__.py
sub_query/tests/db/backends/postgis/test_base.py
sub_query/tests/db/models/__init__.py
sub_query/tests/db/models/test_query.py
sub_query/tests/db/models/sql/__init__.py
sub_query/tests/db/models/sql/test_compiler.py
test_app/__init__.py
test_app/models.py