Metadata-Version: 1.1
Name: django-sub-query
Version: 0.1
Summary: Django app which uses SQL sub-queries to solve some ORM limitations
Home-page: https://github.com/miki725/django-sub-query
Author: Miroslav Shubernetskiy
Author-email: UNKNOWN
License: MIT
Keywords: django
Platform: UNKNOWN
Classifier: Intended Audience :: Developers
Classifier: Natural Language :: English
Classifier: License :: OSI Approved :: MIT License
Classifier: Programming Language :: Python
Classifier: Programming Language :: Python :: 2.7
Classifier: Programming Language :: Python :: 3
Classifier: Programming Language :: Python :: 3.4
Classifier: Development Status :: 2 - Pre-Alpha
